[{"title": "The Best Science Fiction Explores Ideas, Not Just Scenarios", "body": "<p>Science fiction is the literature of ideas — at its best, a form of sustained philosophical and scientific speculation that uses the tools of narrative to explore possibilities that other genres cannot reach. The distinction between serious science fiction and adventure fiction set in space is not snobbery; it is a distinction between two genuinely different things that happen to share some surface features.</p><p>The best science fiction begins with a genuine speculative premise — what if? — and then follows it with rigorous honesty. What if consciousness could be copied? What if faster-than-light travel were possible? What if climate change proceeded to its worst-case conclusions? The speculative premise is not window dressing; it is the engine of the narrative, and the story's job is to explore its implications with genuine intellectual seriousness.</p><p>Ursula K. Le Guin's <em>The Left Hand of Darkness</em> — a novel set on a world whose human inhabitants have no fixed biological sex, experiencing brief periods of fertility in which they can take either male or female role — is not primarily a story about aliens. It is an exploration of what our concepts of gender, sexuality, and social organisation actually are, made visible by their absence. The speculative premise is the lens through which Le Guin examines the scaffolding of human society that is otherwise too familiar to see.</p><p>This is what the best science fiction does: it makes the familiar strange enough to examine. It uses speculative distance to look directly at things that proximity makes invisible. The question 'what would it mean for humanity if X were true?' is the genre's fundamental question, and the depth and honesty of the answer distinguishes the literature from the entertainment.</p>", "publish_date": "2026-03-30", "genre": "Science Fiction"}, {"title": "Dystopia vs Utopia: Why Imagining Bad Futures Is More Useful Than Good Ones", "body": "<p>Dystopian fiction has dominated speculative literature for a century: from Zamyatin's <em>We</em> through Huxley's <em>Brave New World</em> and Orwell's <em>Nineteen Eighty-Four</em> to the recent explosion of young adult dystopia and literary near-future catastrophe. Utopian fiction — imaginings of genuinely better possible worlds — is considerably rarer, and when it appears, it tends to be less compelling narratively and less culturally influential.</p><p>The narrative reason for dystopia's dominance is simple: conflict drives story, and dystopia is defined by conflict between individuals and oppressive systems. Utopia — by definition a world of achieved human flourishing — is dramatically inert. What happens in a world where things have worked out? The answer, for most narrative purposes, is: not much that is interesting to read.</p><p>But the dominance of dystopia has a political dimension as well. Dystopian fiction serves a warning function — it makes vivid the worst-case trajectories of existing tendencies, translating abstract political and technological concerns into the specific and experiential. Orwell's doublethink, Huxley's soma, Atwood's Gilead: these are not predictions but extrapolations, taking features of existing society and following them further than they have yet gone. The discomfort they produce is the point.</p><p>Utopian fiction, when it succeeds, serves a different function: it exercises the imagination of possibility, challenging the unspoken assumption that the present arrangement of things is the best arrangement available. Le Guin's utopias — particularly in <em>The Dispossessed</em> and the Hainish Cycle — are among the most successful, precisely because she is honest about the costs and contradictions of even her best imagined societies. An honest utopia is more challenging, and more useful, than a perfect one.</p>", "publish_date": "2026-04-06", "genre": "Science Fiction"}, {"title": "The Science in Science Fiction: When Authors Get It Right (And Wrong)", "body": "<p>Science fiction has a complicated relationship with actual science. Some SF authors — Kim Stanley Robinson, Neal Stephenson, Arthur C. Clarke — are meticulous about scientific accuracy, researching their premises carefully and extrapolating with rigorous consistency. Others use science as flavouring — a vocabulary of plausible-sounding terminology that creates an atmosphere of scientific legitimacy while departing freely from anything physics would actually permit.</p><p>The most scientifically accurate SF is not always the most useful scientifically. Clarke's <em>2001: A Space Odyssey</em> was scrupulous about orbital mechanics and the experience of zero gravity in ways that influenced a generation of scientists and engineers. Kim Stanley Robinson's Mars trilogy provides what many planetary scientists consider the most accurate fictional account of Mars terraforming available. The Martian by Andy Weir was fact-checked by NASA engineers and served as a useful public demonstration of the actual challenges of Mars exploration.</p><p>But productive scientific inaccuracy has its place. Faster-than-light travel is physically impossible — almost certainly — yet its presence in Star Trek and countless other works has been enormously generative, allowing the exploration of scenarios (first contact, civilisational diversity, time dilation stories) that add genuine value to public thinking about humanity's cosmic future, even though the premise is fantasy.</p><p>The most honest science fiction is transparent about where it departs from the known and where it stays within it — and uses both modes deliberately. The FTL drive might be a conceit, but the social dynamics of a generation ship are worth working through rigorously. The alien might violate biology, but the political consequences of first contact might be extrapolated with genuine intellectual care. The mixture of rigour and imagination is the genre at its most interesting.</p>", "publish_date": "2026-04-13", "genre": "Science Fiction"}, {"title": "Artificial Intelligence in Science Fiction: What the Genre Got Right", "body": "<p>Science fiction has been imagining artificial intelligence since before the field of AI research existed. The genre's track record on the specific details is mixed — it famously failed to predict the internet in anything like its actual form — but its exploration of the philosophical and social dimensions of machine intelligence has been remarkably prescient.</p><p>The questions that dominated early AI research — can machines think? what is the relationship between intelligence and consciousness? — were being explored in fiction decades before they appeared in academic journals. Philip K. Dick's central preoccupation, from <em>Do Androids Dream of Electric Sheep?</em> through dozens of short stories, was precisely the question of what distinguishes a genuine human from a perfect simulation of one — a question that the development of large language models has made suddenly, uncomfortably practical.</p><p>Asimov's Three Laws of Robotics — designed to ensure robots act safely and beneficially — turned out to be a more prescient research programme than their fictional context suggested. The field of AI alignment, which attempts to ensure that AI systems pursue goals aligned with human values, is grappling with exactly the problems Asimov explored narratively: the difficulty of specifying values precisely enough that intelligent optimisers cannot find unexpected and undesirable ways to satisfy them.</p><p>What SF has been less successful at predicting is the form that AI would actually take. Almost no SF envisioned AI as a statistical pattern-matching system trained on text — the dominant paradigm of contemporary AI. The AIs of fiction are almost invariably purposeful, agentive, and in some sense understanding what they process. The reality — enormously capable systems with no understanding whatsoever — is stranger, and in some ways more concerning, than the fictional versions.</p>", "publish_date": "2026-04-20", "genre": "Science Fiction"}, {"title": "First Contact: What Science Fiction Teaches Us About Meeting the Unknown", "body": "<p>First contact — the moment of humanity's initial encounter with extraterrestrial intelligence — is one of science fiction's most enduring narrative premises. From H.G. Wells's invading Martians through Arthur C. Clarke's enigmatic monolith to the linguistic puzzle of Denis Villeneuve's <em>Arrival</em>, the first contact story asks a question that is simultaneously scientific, political, philosophical, and existential: what happens when humanity meets something genuinely, fundamentally Other?</p><p>The most interesting first contact stories are not primarily about aliens. They are about humanity — specifically, about what our responses to the radically different reveal about our assumptions, values, and limitations. The military response (threat assessment, containment) reveals one set of values. The scientific response (curiosity, systematic study) reveals another. The religious response (sacred encounter, cosmic meaning) a third. First contact stories are, in effect, Rorschach tests for human civilisation.</p><p>The linguistic dimension of first contact — how would we actually communicate with an intelligence that did not share our evolutionary history, our sensory apparatus, or our cognitive architecture? — has been explored with genuine rigour by some SF authors, most notably Ted Chiang in the story that became <em>Arrival</em>. The implications of that story — that the structure of language shapes the structure of thought, and that a radically different language might imply a radically different experience of time and causality — draw on real linguistic and cognitive science while extending it into genuinely speculative territory.</p><p>The scientific first contact programme — SETI, the Search for Extraterrestrial Intelligence — has been running for over sixty years without confirmed success. What SF has provided, in the absence of actual contact, is a rehearsal space for thinking about what contact would mean — and how we would want to respond.</p>", "publish_date": "2026-04-27", "genre": "Science Fiction"}, {"title": "Why Science Fiction Readers Make Better Futurists", "body": "<p>The future is not predictable, but it is not random either. It emerges from the interactions of existing trends, technologies, social arrangements, and human decisions — and it can be reasoned about, at least probabilistically, by minds that have practised the relevant kind of thinking. Science fiction, at its best, trains exactly that kind of thinking.</p><p>The core cognitive skill that SF develops is what Darko Suvin called 'cognitive estrangement': the ability to take a familiar world and imagine it changed in a specific, consistent way, then to reason carefully about what would follow from that change. This is not fantasy — it is not the arbitrary introduction of magic — but a disciplined form of conditional reasoning. If X were true, what else would have to be true? What would change, and what would stay the same? What second and third-order effects would follow?</p><p>This skill is precisely what is required for effective strategic planning, policy analysis, and technology assessment — all domains in which the ability to reason rigorously about possible futures is essential. The failure modes of these domains — tunnel vision, planning for one future, failure to model second-order effects — are exactly what extensive engagement with speculative fiction trains against.</p><p>The research on this is limited but suggestive: studies have found that readers of literary fiction have better theory of mind (the ability to model other people's mental states) than non-readers; similar effects might plausibly be hypothesised for the specific cognitive skills that SF exercises. What is less speculative is the testimony of practitioners: numerous scientists, technologists, and policy-makers have cited SF as formative in developing their capacity to think about the future with both rigour and imagination.</p>", "publish_date": "2026-05-04", "genre": "Science Fiction"}]